.Rhistory
.gitignore
MANIFEST.in
README.md
README.pypi
setup.py
Orange3_sma.egg-info/PKG-INFO
Orange3_sma.egg-info/SOURCES.txt
Orange3_sma.egg-info/dependency_links.txt
Orange3_sma.egg-info/entry_points.txt
Orange3_sma.egg-info/namespace_packages.txt
Orange3_sma.egg-info/not-zip-safe
Orange3_sma.egg-info/requires.txt
Orange3_sma.egg-info/top_level.txt
doc/Makefile
doc/conf.py
doc/index.rst
doc/make.bat
doc/widgets/OWAmcat.md
doc/widgets/OWCorpusStatistics.md
doc/widgets/OWDictionary.md
doc/widgets/OWFacebook.md
doc/widgets/OWFilter.md
doc/widgets/OWPosFilter.md
doc/widgets/icons/DataSamplerA.svg
doc/widgets/icons/amcat-logo.svg
doc/widgets/icons/dictionary.svg
doc/widgets/icons/facebook-logo.svg
doc/widgets/icons/filter.svg
doc/widgets/icons/queryfilter.svg
doc/widgets/icons/stats.svg
orangecontrib/__init__.py
orangecontrib/sma/__init__.py
orangecontrib/sma/facebook_orange_api.py
orangecontrib/sma/index.py
orangecontrib/sma/tutorials/__init__.py
orangecontrib/sma/tutorials/supervised_machine_learning.ows
orangecontrib/sma/widgets/OWAmcat.py
orangecontrib/sma/widgets/OWCorpusStatistics.py
orangecontrib/sma/widgets/OWDictionary.py
orangecontrib/sma/widgets/OWFacebook.py
orangecontrib/sma/widgets/OWFilter.py
orangecontrib/sma/widgets/OWPosFilter.py
orangecontrib/sma/widgets/__init__.py
orangecontrib/sma/widgets/icons/DataSamplerA.svg
orangecontrib/sma/widgets/icons/amcat-logo.svg
orangecontrib/sma/widgets/icons/dictionary.svg
orangecontrib/sma/widgets/icons/facebook-logo.svg
orangecontrib/sma/widgets/icons/filter.svg
orangecontrib/sma/widgets/icons/queryfilter.svg
orangecontrib/sma/widgets/icons/stats.svg