Metadata-Version: 1.0
Name: Orange3-sma
Version: 0.3.2
Summary: Provides widgets for social media analytics
Home-page: UNKNOWN
Author: UNKNOWN
Author-email: UNKNOWN
License: BSD
Keywords: orange3 add-on,orange3-sma
Platform: UNKNOWN
